librehardwaremonitor_api/__init__.py
librehardwaremonitor_api/client.py
librehardwaremonitor_api/errors.py
librehardwaremonitor_api/model.py
librehardwaremonitor_api/parser.py
librehardwaremonitor_api/py.typed
librehardwaremonitor_api-1.8.4.dist-info/METADATA
librehardwaremonitor_api-1.8.4.dist-info/WHEEL
librehardwaremonitor_api-1.8.4.dist-info/licenses/LICENSE.md
librehardwaremonitor_api-1.8.4.dist-info/RECORD
