Metadata-Version: 2.4
Name: librehardwaremonitor-api
Version: 1.8.4
Summary: A Python API client for LibreHardwareMonitor
Project-URL: Homepage, https://github.com/Sab44/librehardwaremonitor-api
Author-email: Sab44 <64696149+Sab44@users.noreply.github.com>
License-Expression: MIT
License-File: LICENSE.md
Classifier: License :: OSI Approved :: MIT License
Classifier: Operating System :: OS Independent
Classifier: Programming Language :: Python :: 3
Requires-Python: >=3.11
Requires-Dist: aiohttp
